hapy/__init__.py
hapy/exector.py
hapy/generate_py.py
hapy/hello.hapy
hapy/importer.py
hapy/indent.py
hapy/input_stream.py
hapy/main.py
hapy/something.hapy
hapy/test_generatepy.py
hapy/test_input_stream.py
hapy/test_parser.py
hapy/test_token_stream.py
hapy/token_parser.py
hapy/token_stream.py
hapy/translations.py
hapy/transpiler.py
hapy/modules/popo_module.py
hapy/modules/test_module.py
scripts/__init__.py
scripts/hapy_cli.py
tests/__init__.py
tests/test_generatepy.py
tests/test_input_stream.py
tests/test_parser.py
tests/test_token_stream.py
hapy-0.5.3.dist-info/LICENSE.txt
hapy-0.5.3.dist-info/METADATA
hapy-0.5.3.dist-info/WHEEL
hapy-0.5.3.dist-info/entry_points.txt
hapy-0.5.3.dist-info/top_level.txt
hapy-0.5.3.dist-info/RECORD
