Metadata-Version: 2.1
Name: hapy
Version: 0.5.3
Summary: Basic Python using Hausa vocabulary
Home-page: https://github.com/hapy-lang/hapy
Author: Emmanuel Segun-Lean
Author-email: emmanuel.segunlean@proton.me
License: MIT
Classifier: Programming Language :: Python :: 3.7
Classifier: Operating System :: OS Independent
Classifier: Intended Audience :: Education
Classifier: Topic :: Education
Classifier: Topic :: Software Development
Requires-Python: >=3.7
License-File: LICENSE.txt
Requires-Dist: click (==8.0.3)
Requires-Dist: click-default-group (==1.2.2)
Requires-Dist: colorama (==0.4.4)
